odoo8_addon_pos_ticket_logo-8.0.1.0.0-py2.7-nspkg.pth
odoo8_addon_pos_ticket_logo-8.0.1.0.0.dist-info/DESCRIPTION.rst
odoo8_addon_pos_ticket_logo-8.0.1.0.0.dist-info/METADATA
odoo8_addon_pos_ticket_logo-8.0.1.0.0.dist-info/RECORD
odoo8_addon_pos_ticket_logo-8.0.1.0.0.dist-info/WHEEL
odoo8_addon_pos_ticket_logo-8.0.1.0.0.dist-info/metadata.json
odoo8_addon_pos_ticket_logo-8.0.1.0.0.dist-info/namespace_packages.txt
odoo8_addon_pos_ticket_logo-8.0.1.0.0.dist-info/top_level.txt
odoo_addons/pos_ticket_logo/README.rst
odoo_addons/pos_ticket_logo/__init__.py
odoo_addons/pos_ticket_logo/__openerp__.py
odoo_addons/pos_ticket_logo/static/description/icon.png
odoo_addons/pos_ticket_logo/static/src/js/main.js
odoo_addons/pos_ticket_logo/static/src/xml/pos.xml
odoo_addons/pos_ticket_logo/views/pos_template.xml
odoo_addons/pos_ticket_logo/views/pos_ticket_logo_report_receipt_report.xml
