Metadata-Version: 2.0
Name: odoo8-addon-pos-ticket-logo
Version: 8.0.1.0.0
Summary: Pos ticket logo
Home-page: http://www.antiun.com
Author: Antiun Ingeniería S.L.
Author-email: UNKNOWN
License: AGPL-3
Platform: UNKNOWN
Classifier: Programming Language :: Python :: 2.7
Classifier: Framework :: Odoo
Classifier: License :: OSI Approved :: GNU Affero General Public License v3
Requires-Dist: odoo (<9.0a,>=8.0a)
